{"ids_to_process":{"json":[{"id":"59214?active=1"},{"id":"59215?active=1"},{"id":"59216?active=1"},{"id":"59369?active=1"},{"id":"59370?active=1"},{"id":"59365?active=1"},{"id":"59367?active=1"},{"id":"59031?active=1"},{"id":"59362?active=1"},{"id":"59358?active=1"},{"id":"59346?active=1"},{"id":"59348?active=1"},{"id":"59351?active=1"},{"id":"59352?active=1"},{"id":"59353?active=1"},{"id":"59355?active=1"},{"id":"59356?active=1"},{"id":"59364?active=1"},{"id":"59361?active=1"}],"db":[{"id":"59214?active=1"},{"id":"59215?active=1"},{"id":"59216?active=1"},{"id":"59369?active=1"},{"id":"59370?active=1"},{"id":"59365?active=1"},{"id":"59367?active=1"},{"id":"59031?active=1"},{"id":"59362?active=1"},{"id":"59358?active=1"},{"id":"59346?active=1"},{"id":"59348?active=1"},{"id":"59351?active=1"},{"id":"59352?active=1"},{"id":"59353?active=1"},{"id":"59355?active=1"},{"id":"59356?active=1"},{"id":"59364?active=1"},{"id":"59361?active=1"}]}}