{"ids_to_process":{"json":[{"id":"58159?active=1"},{"id":"58147?active=1"},{"id":"58149?active=1"},{"id":"58150?active=1"},{"id":"58146?active=1"},{"id":"58157?active=1"},{"id":"58151?active=1"},{"id":"58163?active=1"},{"id":"58158?active=1"},{"id":"58145?active=1"},{"id":"58161?active=1"},{"id":"58140?active=1"},{"id":"58138?active=1"},{"id":"58137?active=1"},{"id":"58136?active=1"},{"id":"58139?active=1"},{"id":"58148?active=1"},{"id":"58152?active=1"},{"id":"58154?active=1"},{"id":"58135?active=1"}],"db":[{"id":"58159?active=1"},{"id":"58147?active=1"},{"id":"58149?active=1"},{"id":"58150?active=1"},{"id":"58146?active=1"},{"id":"58157?active=1"},{"id":"58151?active=1"},{"id":"58163?active=1"},{"id":"58158?active=1"},{"id":"58145?active=1"},{"id":"58161?active=1"},{"id":"58140?active=1"},{"id":"58138?active=1"},{"id":"58137?active=1"},{"id":"58136?active=1"},{"id":"58139?active=1"},{"id":"58148?active=1"},{"id":"58152?active=1"},{"id":"58154?active=1"},{"id":"58135?active=1"}]}}