{"ids_to_process":{"json":[{"id":"49895?active=1"},{"id":"49852?active=1"},{"id":"49854?active=1"},{"id":"49848?active=1"},{"id":"49851?active=1"},{"id":"49855?active=1"},{"id":"49865?active=1"},{"id":"49856?active=1"},{"id":"49880?active=1"},{"id":"49857?active=1"},{"id":"49860?active=1"},{"id":"49853?active=1"},{"id":"49846?active=1"},{"id":"49878?active=1"},{"id":"49881?active=1"},{"id":"49876?active=1"},{"id":"49882?active=1"},{"id":"49870?active=1"},{"id":"49874?active=1"},{"id":"49864?active=1"},{"id":"49862?active=1"},{"id":"49798?active=1"},{"id":"49859?active=1"}],"db":[{"id":"49895?active=1"},{"id":"49852?active=1"},{"id":"49854?active=1"},{"id":"49848?active=1"},{"id":"49851?active=1"},{"id":"49855?active=1"},{"id":"49865?active=1"},{"id":"49856?active=1"},{"id":"49880?active=1"},{"id":"49857?active=1"},{"id":"49860?active=1"},{"id":"49853?active=1"},{"id":"49846?active=1"},{"id":"49878?active=1"},{"id":"49881?active=1"},{"id":"49876?active=1"},{"id":"49882?active=1"},{"id":"49870?active=1"},{"id":"49874?active=1"},{"id":"49864?active=1"},{"id":"49862?active=1"},{"id":"49798?active=1"},{"id":"49859?active=1"}]}}