{"ids_to_process":{"json":[{"id":"55880?active=1"},{"id":"55875?active=1"},{"id":"55865?active=1"},{"id":"55867?active=1"},{"id":"55868?active=1"},{"id":"55866?active=1"},{"id":"55839?active=1"},{"id":"55858?active=1"},{"id":"55854?active=1"},{"id":"55863?active=1"},{"id":"55864?active=1"},{"id":"55813?active=1"},{"id":"55847?active=1"},{"id":"55806?active=1"},{"id":"55807?active=1"},{"id":"55810?active=1"},{"id":"55811?active=1"},{"id":"55812?active=1"},{"id":"55842?active=1"},{"id":"55843?active=1"},{"id":"55845?active=1"},{"id":"55848?active=1"},{"id":"55859?active=1"},{"id":"55798?active=1"},{"id":"55752?active=1"},{"id":"55852?active=1"},{"id":"55856?active=1"}],"db":[{"id":"55880?active=1"},{"id":"55875?active=1"},{"id":"55865?active=1"},{"id":"55867?active=1"},{"id":"55868?active=1"},{"id":"55866?active=1"},{"id":"55839?active=1"},{"id":"55858?active=1"},{"id":"55854?active=1"},{"id":"55863?active=1"},{"id":"55864?active=1"},{"id":"55813?active=1"},{"id":"55847?active=1"},{"id":"55806?active=1"},{"id":"55807?active=1"},{"id":"55810?active=1"},{"id":"55811?active=1"},{"id":"55812?active=1"},{"id":"55842?active=1"},{"id":"55843?active=1"},{"id":"55845?active=1"},{"id":"55848?active=1"},{"id":"55859?active=1"},{"id":"55798?active=1"},{"id":"55752?active=1"},{"id":"55852?active=1"},{"id":"55856?active=1"}]}}