{"ids_to_process":{"json":[{"id":"59200?active=1"},{"id":"59124?active=1"},{"id":"59191?active=1"},{"id":"59192?active=1"},{"id":"59194?active=1"},{"id":"59195?active=1"},{"id":"59163?active=1"},{"id":"59161?active=1"},{"id":"59160?active=1"},{"id":"59164?active=1"},{"id":"59180?active=1"},{"id":"59197?active=1"},{"id":"59196?active=1"},{"id":"59140?active=1"},{"id":"59142?active=1"},{"id":"59141?active=1"},{"id":"59145?active=1"},{"id":"59146?active=1"},{"id":"59144?active=1"},{"id":"59147?active=1"},{"id":"59152?active=1"},{"id":"59183?active=1"},{"id":"59182?active=1"},{"id":"59155?active=1"}],"db":[{"id":"59200?active=1"},{"id":"59124?active=1"},{"id":"59191?active=1"},{"id":"59192?active=1"},{"id":"59194?active=1"},{"id":"59195?active=1"},{"id":"59163?active=1"},{"id":"59161?active=1"},{"id":"59160?active=1"},{"id":"59164?active=1"},{"id":"59180?active=1"},{"id":"59197?active=1"},{"id":"59196?active=1"},{"id":"59140?active=1"},{"id":"59142?active=1"},{"id":"59141?active=1"},{"id":"59145?active=1"},{"id":"59146?active=1"},{"id":"59144?active=1"},{"id":"59147?active=1"},{"id":"59152?active=1"},{"id":"59183?active=1"},{"id":"59182?active=1"},{"id":"59155?active=1"}]}}